raachem/__init__.py
raachem/__main__.py
raachem/file_class/__init__.py
raachem/file_class/gjf.py
raachem/file_class/inp.py
raachem/file_class/log.py
raachem/file_class/xyz.py
raachem/file_creator/__init__.py
raachem/file_creator/deploy_scripts.py
raachem/file_creator/e_analysis.py
raachem/file_creator/input.py
raachem/file_creator/xyz.py
raachem/file_creator/builtin_templates/DLNPO_CCSDT.ORCA
raachem/file_creator/builtin_templates/IRC.GAUSSIAN
raachem/file_creator/builtin_templates/OPT_FREQ.GAUSSIAN
raachem/file_creator/builtin_templates/READ_ATOMS.GAUSSIAN
raachem/file_creator/builtin_templates/READ_NOTATOMS.GAUSSIAN
raachem/file_creator/builtin_templates/SCAN_APROX.GAUSSIAN
raachem/file_creator/builtin_templates/SCAN_DIHEDRAL.GAUSSIAN
raachem/file_creator/builtin_templates/SCAN_DIST.GAUSSIAN
raachem/file_creator/builtin_templates/SP_BASIS.GAUSSIAN
raachem/file_creator/builtin_templates/SP_def2TZVP.GAUSSIAN
raachem/file_creator/builtin_templates/TS_FREQ.GAUSSIAN
raachem/file_creator/builtin_templates/__init__.py
raachem/file_creator/builtin_templates/def2-tzvpd.1.gbs
raachem/file_creator/par_templates/__init__.py
raachem/file_creator/scripts/__init__.py
raachem/file_creator/scripts/cleanup.py
raachem/file_creator/scripts/n_jobs_sub.py
raachem/file_creator/scripts/run_jobs.py
raachem/util/__init__.py
raachem/util/constants.py
raachem/util/gen_purp.py
raachem/util/interface.py
raachem-0.0.8.post2.dist-info/LICENSE.txt
raachem-0.0.8.post2.dist-info/METADATA
raachem-0.0.8.post2.dist-info/WHEEL
raachem-0.0.8.post2.dist-info/top_level.txt
raachem-0.0.8.post2.dist-info/RECORD
