Metadata-Version: 2.1
Name: raachem
Version: 0.0.8.post2
Summary: Tools I use for computational chemistry
Home-page: https://github.com/ricalmang/raachem
Author: Ricardo Almir Angnes
Author-email: ricardo_almir@hotmail.com
License: MIT
Keywords: chemistry
Platform: UNKNOWN
Classifier: Programming Language :: Python :: 3
Classifier: License :: OSI Approved :: MIT License
Classifier: Operating System :: OS Independent
Requires-Python: >=3.6
Requires-Dist: numpy
Requires-Dist: xlwt
